agentkit/__init__.py
agentkit/databus.py
agentkit/handlers.py
agentkit/messages.py
agentkit/network.py
agentkit/processor.py
agentkit/agents/__init__.py
agentkit/agents/simple_agent.py
agentkit/brains/__init__.py
agentkit/brains/simple_brain.py
agentkit/examples/human_agent.py
agentkit/examples/simple_chat_agent.py
agentkit/examples/config/simple_chat.json
agentkit/io/__init__.py
agentkit/io/console.py
agentkit/memory/__init__.py
agentkit/memory/memory_protocol.py
agentkit/memory/simple_memory.py
agentkit-0.0.1.dist-info/METADATA
agentkit-0.0.1.dist-info/WHEEL
agentkit-0.0.1.dist-info/licenses/LICENSE
agentkit-0.0.1.dist-info/RECORD
