Metadata-Version: 2.3
Name: agentkit
Version: 0.0.1
Summary: A simple framework for creating distributed llm agent swarms
Project-URL: Repository, https://github.com/japanvik/agentkit
Author-email: Vikram Kumar <vik@japanvik.net>
License: MIT License
License-File: LICENSE
Keywords: artificial intelligencs,llm,pubsub
Classifier: Development Status :: 4 - Beta
Classifier: Programming Language :: Python
Requires-Python: >=3.8
Requires-Dist: fastapi
Requires-Dist: litellm
Requires-Dist: pydantic
Requires-Dist: uvicorn
Requires-Dist: zmq
